wahoo/__init__.py
wahoo/map.py
wahoo-0.0.1.dist-info/LICENSE.txt
wahoo-0.0.1.dist-info/METADATA
wahoo-0.0.1.dist-info/WHEEL
wahoo-0.0.1.dist-info/top_level.txt
wahoo-0.0.1.dist-info/RECORD
