Metadata-Version: 2.1
Name: wahoo
Version: 0.0.1
Summary: Wahoo placeholder
Home-page: https://github.com/nanoporetech/taiyaki
Author: Allan Evans
Author-email: allan.evans@nanoporetech.com
License: UNKNOWN
Platform: UNKNOWN
Classifier: Programming Language :: Python :: 3
Classifier: License :: OSI Approved :: MIT License
Classifier: Operating System :: OS Independent
Requires-Python: >=3.6
